[{"model": "admin.logentry", "pk": 1, "fields": {"action_time": "2025-07-21T15:00:15.333Z", "user": 1, "content_type": 7, "object_id": "1", "object_repr": "CPL-1 - bertaqwa kepada tuhan", "action_flag": 1, "change_message": "[{\"added\": {}}]"}}, {"model": "admin.logentry", "pk": 2, "fields": {"action_time": "2025-07-21T15:00:34.696Z", "user": 1, "content_type": 7, "object_id": "2", "object_repr": "CPL-2 - Mengelola manajemen dengan baik", "action_flag": 1, "change_message": "[{\"added\": {}}]"}}, {"model": "admin.logentry", "pk": 3, "fields": {"action_time": "2025-07-21T15:01:40.399Z", "user": 1, "content_type": 8, "object_id": "1", "object_repr": "123 - Matematika Teknik", "action_flag": 1, "change_message": "[{\"added\": {}}, {\"added\": {\"name\": \"matakuliah cpl\", \"object\": \"MatakuliahCPL object (1)\"}}, {\"added\": {\"name\": \"matakuliah cpl\", \"object\": \"MatakuliahCPL object (2)\"}}]"}}, {"model": "admin.logentry", "pk": 4, "fields": {"action_time": "2025-07-21T15:05:04.988Z", "user": 1, "content_type": 10, "object_id": "1", "object_repr": "CPMK1 - cpmk1 denang cpl a", "action_flag": 1, "change_message": "[{\"added\": {}}]"}}, {"model": "admin.logentry", "pk": 5, "fields": {"action_time": "2025-07-21T15:05:30.935Z", "user": 1, "content_type": 10, "object_id": "2", "object_repr": "ckmd - menjadi anak soleh cpl2", "action_flag": 1, "change_message": "[{\"added\": {}}]"}}, {"model": "admin.logentry", "pk": 6, "fields": {"action_time": "2025-07-21T15:06:12.896Z", "user": 1, "content_type": 11, "object_id": "1", "object_repr": "abc - asd", "action_flag": 1, "change_message": "[{\"added\": {}}]"}}, {"model": "auth.permission", "pk": 1, "fields": {"name": "Can add log entry", "content_type": 1, "codename": "add_logentry"}}, {"model": "auth.permission", "pk": 2, "fields": {"name": "Can change log entry", "content_type": 1, "codename": "change_logentry"}}, {"model": "auth.permission", "pk": 3, "fields": {"name": "Can delete log entry", "content_type": 1, "codename": "delete_logentry"}}, {"model": "auth.permission", "pk": 4, "fields": {"name": "Can view log entry", "content_type": 1, "codename": "view_logentry"}}, {"model": "auth.permission", "pk": 5, "fields": {"name": "Can add permission", "content_type": 2, "codename": "add_permission"}}, {"model": "auth.permission", "pk": 6, "fields": {"name": "Can change permission", "content_type": 2, "codename": "change_permission"}}, {"model": "auth.permission", "pk": 7, "fields": {"name": "Can delete permission", "content_type": 2, "codename": "delete_permission"}}, {"model": "auth.permission", "pk": 8, "fields": {"name": "Can view permission", "content_type": 2, "codename": "view_permission"}}, {"model": "auth.permission", "pk": 9, "fields": {"name": "Can add group", "content_type": 3, "codename": "add_group"}}, {"model": "auth.permission", "pk": 10, "fields": {"name": "Can change group", "content_type": 3, "codename": "change_group"}}, {"model": "auth.permission", "pk": 11, "fields": {"name": "Can delete group", "content_type": 3, "codename": "delete_group"}}, {"model": "auth.permission", "pk": 12, "fields": {"name": "Can view group", "content_type": 3, "codename": "view_group"}}, {"model": "auth.permission", "pk": 13, "fields": {"name": "Can add user", "content_type": 4, "codename": "add_user"}}, {"model": "auth.permission", "pk": 14, "fields": {"name": "Can change user", "content_type": 4, "codename": "change_user"}}, {"model": "auth.permission", "pk": 15, "fields": {"name": "Can delete user", "content_type": 4, "codename": "delete_user"}}, {"model": "auth.permission", "pk": 16, "fields": {"name": "Can view user", "content_type": 4, "codename": "view_user"}}, {"model": "auth.permission", "pk": 17, "fields": {"name": "Can add content type", "content_type": 5, "codename": "add_contenttype"}}, {"model": "auth.permission", "pk": 18, "fields": {"name": "Can change content type", "content_type": 5, "codename": "change_contenttype"}}, {"model": "auth.permission", "pk": 19, "fields": {"name": "Can delete content type", "content_type": 5, "codename": "delete_contenttype"}}, {"model": "auth.permission", "pk": 20, "fields": {"name": "Can view content type", "content_type": 5, "codename": "view_contenttype"}}, {"model": "auth.permission", "pk": 21, "fields": {"name": "Can add session", "content_type": 6, "codename": "add_session"}}, {"model": "auth.permission", "pk": 22, "fields": {"name": "Can change session", "content_type": 6, "codename": "change_session"}}, {"model": "auth.permission", "pk": 23, "fields": {"name": "Can delete session", "content_type": 6, "codename": "delete_session"}}, {"model": "auth.permission", "pk": 24, "fields": {"name": "Can view session", "content_type": 6, "codename": "view_session"}}, {"model": "auth.permission", "pk": 25, "fields": {"name": "Can add cpl", "content_type": 7, "codename": "add_cpl"}}, {"model": "auth.permission", "pk": 26, "fields": {"name": "Can change cpl", "content_type": 7, "codename": "change_cpl"}}, {"model": "auth.permission", "pk": 27, "fields": {"name": "Can delete cpl", "content_type": 7, "codename": "delete_cpl"}}, {"model": "auth.permission", "pk": 28, "fields": {"name": "Can view cpl", "content_type": 7, "codename": "view_cpl"}}, {"model": "auth.permission", "pk": 29, "fields": {"name": "Can add matakuliah", "content_type": 8, "codename": "add_matakuliah"}}, {"model": "auth.permission", "pk": 30, "fields": {"name": "Can change matakuliah", "content_type": 8, "codename": "change_matakuliah"}}, {"model": "auth.permission", "pk": 31, "fields": {"name": "Can delete matakuliah", "content_type": 8, "codename": "delete_matakuliah"}}, {"model": "auth.permission", "pk": 32, "fields": {"name": "Can view matakuliah", "content_type": 8, "codename": "view_matakuliah"}}, {"model": "auth.permission", "pk": 33, "fields": {"name": "Can add matakuliah cpl", "content_type": 9, "codename": "add_matakuliahcpl"}}, {"model": "auth.permission", "pk": 34, "fields": {"name": "Can change matakuliah cpl", "content_type": 9, "codename": "change_matakuliahcpl"}}, {"model": "auth.permission", "pk": 35, "fields": {"name": "Can delete matakuliah cpl", "content_type": 9, "codename": "delete_matakuliahcpl"}}, {"model": "auth.permission", "pk": 36, "fields": {"name": "Can view matakuliah cpl", "content_type": 9, "codename": "view_matakuliahcpl"}}, {"model": "auth.permission", "pk": 37, "fields": {"name": "Can add cpmk", "content_type": 10, "codename": "add_cpmk"}}, {"model": "auth.permission", "pk": 38, "fields": {"name": "Can change cpmk", "content_type": 10, "codename": "change_cpmk"}}, {"model": "auth.permission", "pk": 39, "fields": {"name": "Can delete cpmk", "content_type": 10, "codename": "delete_cpmk"}}, {"model": "auth.permission", "pk": 40, "fields": {"name": "Can view cpmk", "content_type": 10, "codename": "view_cpmk"}}, {"model": "auth.permission", "pk": 41, "fields": {"name": "Can add sub cpmk", "content_type": 11, "codename": "add_subcpmk"}}, {"model": "auth.permission", "pk": 42, "fields": {"name": "Can change sub cpmk", "content_type": 11, "codename": "change_subcpmk"}}, {"model": "auth.permission", "pk": 43, "fields": {"name": "Can delete sub cpmk", "content_type": 11, "codename": "delete_subcpmk"}}, {"model": "auth.permission", "pk": 44, "fields": {"name": "Can view sub cpmk", "content_type": 11, "codename": "view_subcpmk"}}, {"model": "auth.user", "pk": 1, "fields": {"password": "pbkdf2_sha256$1000000$Poin2HouXJZsZZ9szlguYc$9MpFx+A137A7MGw8B9JjoXzg6G1OpU+vsyE7MXLelqw=", "last_login": "2025-07-21T14:54:33.483Z", "is_superuser": true, "username": "elektro", "first_name": "", "last_name": "", "email": "elektro@upgris.ac.id", "is_staff": true, "is_active": true, "date_joined": "2025-07-21T14:54:09.953Z", "groups": [], "user_permissions": []}}, {"model": "contenttypes.contenttype", "pk": 1, "fields": {"app_label": "admin", "model": "logentry"}}, {"model": "contenttypes.contenttype", "pk": 2, "fields": {"app_label": "auth", "model": "permission"}}, {"model": "contenttypes.contenttype", "pk": 3, "fields": {"app_label": "auth", "model": "group"}}, {"model": "contenttypes.contenttype", "pk": 4, "fields": {"app_label": "auth", "model": "user"}}, {"model": "contenttypes.contenttype", "pk": 5, "fields": {"app_label": "contenttypes", "model": "contenttype"}}, {"model": "contenttypes.contenttype", "pk": 6, "fields": {"app_label": "sessions", "model": "session"}}, {"model": "contenttypes.contenttype", "pk": 7, "fields": {"app_label": "kurikulum", "model": "cpl"}}, {"model": "contenttypes.contenttype", "pk": 8, "fields": {"app_label": "kurikulum", "model": "matakuliah"}}, {"model": "contenttypes.contenttype", "pk": 9, "fields": {"app_label": "kurikulum", "model": "matakuliahcpl"}}, {"model": "contenttypes.contenttype", "pk": 10, "fields": {"app_label": "kurikulum", "model": "cpmk"}}, {"model": "contenttypes.contenttype", "pk": 11, "fields": {"app_label": "kurikulum", "model": "subcpmk"}}, {"model": "sessions.session", "pk": "usqnf56grmf99zzdwu1jh0is8fdxtgn8", "fields": {"session_data": ".eJxVjEEOwiAQRe_C2pCBEUdcuu8ZGpihUjWQlHZlvLuSdKHb997_LzWGbc3j1tIyzqIuyqjDL4uBH6l0IfdQblVzLesyR90Tvdumhyrped3bv4McWu5r8UheUrLoDE1AyA6AvT0RJmJjCL9YYowOPJsJznD0gGCsRUGy6v0By042og:1udruT:CqCGxc3suLw7O3Y6iHnT3uOiw19DyLzL5ZCaTs05SNY", "expire_date": "2025-08-04T14:54:33.486Z"}}, {"model": "kurikulum.cpl", "pk": 1, "fields": {"kode": "CPL-1", "deskripsi": "bertaqwa kepada tuhan", "kategori": "sikap"}}, {"model": "kurikulum.cpl", "pk": 2, "fields": {"kode": "CPL-2", "deskripsi": "Mengelola manajemen dengan baik", "kategori": "pengetahuan"}}, {"model": "kurikulum.matakuliah", "pk": 1, "fields": {"kode": "123", "nama": "Matematika Teknik", "sks": 3, "semester": 2, "pelaksanaan": 1, "kelompokmk": 3}}, {"model": "kurikulum.matakuliahcpl", "pk": 1, "fields": {"matakuliah": 1, "cpl": 1}}, {"model": "kurikulum.matakuliahcpl", "pk": 2, "fields": {"matakuliah": 1, "cpl": 2}}, {"model": "kurikulum.cpmk", "pk": 1, "fields": {"kode": "CPMK1", "deskripsi": "cpmk1 denang cpl a", "matakuliah": 1, "cpl": 1}}, {"model": "kurikulum.cpmk", "pk": 2, "fields": {"kode": "ckmd", "deskripsi": "menjadi anak soleh cpl2", "matakuliah": 1, "cpl": 2}}, {"model": "kurikulum.subcpmk", "pk": 1, "fields": {"kode": "abc", "deskripsi": "asd", "cpmk": 1, "durasi": 5, "bentuk": "teori", "indikator": "Mampu memahami...."}}]